<?xml version="1.0" encoding="UTF-8" ?>
<!DOCTYPE mapper PUBLIC "-//mybatis.org//DTD Mapper 3.0//EN" "http://mybatis.org/dtd/mybatis-3-mapper.dtd" >
<mapper namespace="com.kf.data.mybatis.mapper.online.TdxUpIndexOnlineMapper" >
  <resultMap id="BaseResultMap" type="com.kf.data.mybatis.entity.online.TdxUpIndexOnline" >
    <!--
      WARNING - @mbggenerated
      This element is automatically generated by MyBatis Generator, do not modify.
      This element was generated on Wed Mar 14 15:34:20 CST 2018.
    -->
    <id column="id" property="id" jdbcType="INTEGER" />
    <result column="table" property="table" jdbcType="VARCHAR" />
    <result column="uptime" property="uptime" jdbcType="TIMESTAMP" />
    <result column="upid" property="upid" jdbcType="INTEGER" />
  </resultMap>
  <sql id="Example_Where_Clause" >
    <!--
      WARNING - @mbggenerated
      This element is automatically generated by MyBatis Generator, do not modify.
      This element was generated on Wed Mar 14 15:34:20 CST 2018.
    -->
    <where >
      <foreach collection="oredCriteria" item="criteria" separator="or" >
        <if test="criteria.valid" >
          <trim prefix="(" suffix=")" prefixOverrides="and" >
            <foreach collection="criteria.criteria" item="criterion" >
              <choose >
                <when test="criterion.noValue" >
                  and ${criterion.condition}
                </when>
                <when test="criterion.singleValue" >
                  and ${criterion.condition} #{criterion.value}
                </when>
                <when test="criterion.betweenValue" >
                  and ${criterion.condition} #{criterion.value} and #{criterion.secondValue}
                </when>
                <when test="criterion.listValue" >
                  and ${criterion.condition}
                  <foreach collection="criterion.value" item="listItem" open="(" close=")" separator="," >
                    #{listItem}
                  </foreach>
                </when>
              </choose>
            </foreach>
          </trim>
        </if>
      </foreach>
    </where>
  </sql>
  <sql id="Update_By_Example_Where_Clause" >
    <!--
      WARNING - @mbggenerated
      This element is automatically generated by MyBatis Generator, do not modify.
      This element was generated on Wed Mar 14 15:34:20 CST 2018.
    -->
    <where >
      <foreach collection="example.oredCriteria" item="criteria" separator="or" >
        <if test="criteria.valid" >
          <trim prefix="(" suffix=")" prefixOverrides="and" >
            <foreach collection="criteria.criteria" item="criterion" >
              <choose >
                <when test="criterion.noValue" >
                  and ${criterion.condition}
                </when>
                <when test="criterion.singleValue" >
                  and ${criterion.condition} #{criterion.value}
                </when>
                <when test="criterion.betweenValue" >
                  and ${criterion.condition} #{criterion.value} and #{criterion.secondValue}
                </when>
                <when test="criterion.listValue" >
                  and ${criterion.condition}
                  <foreach collection="criterion.value" item="listItem" open="(" close=")" separator="," >
                    #{listItem}
                  </foreach>
                </when>
              </choose>
            </foreach>
          </trim>
        </if>
      </foreach>
    </where>
  </sql>
  <sql id="Base_Column_List" >
    <!--
      WARNING - @mbggenerated
      This element is automatically generated by MyBatis Generator, do not modify.
      This element was generated on Wed Mar 14 15:34:20 CST 2018.
    -->
    id, `table`, uptime, upid
  </sql>
  <select id="selectByExample" resultMap="BaseResultMap" parameterType="com.kf.data.mybatis.entity.online.TdxUpIndexOnlineExample" >
    <!--
      WARNING - @mbggenerated
      This element is automatically generated by MyBatis Generator, do not modify.
      This element was generated on Wed Mar 14 15:34:20 CST 2018.
    -->
    select
    <if test="distinct" >
      distinct
    </if>
    <include refid="Base_Column_List" />
    from tdx_up_index
    <if test="_parameter != null" >
      <include refid="Example_Where_Clause" />
    </if>
    <if test="orderByClause != null" >
      order by ${orderByClause}
    </if>
  </select>
  <select id="selectByPrimaryKey" resultMap="BaseResultMap" parameterType="java.lang.Integer" >
    <!--
      WARNING - @mbggenerated
      This element is automatically generated by MyBatis Generator, do not modify.
      This element was generated on Wed Mar 14 15:34:20 CST 2018.
    -->
    select 
    <include refid="Base_Column_List" />
    from tdx_up_index
    where id = #{id,jdbcType=INTEGER}
  </select>
  <delete id="deleteByPrimaryKey" parameterType="java.lang.Integer" >
    <!--
      WARNING - @mbggenerated
      This element is automatically generated by MyBatis Generator, do not modify.
      This element was generated on Wed Mar 14 15:34:20 CST 2018.
    -->
    delete from tdx_up_index
    where id = #{id,jdbcType=INTEGER}
  </delete>
  <delete id="deleteByExample" parameterType="com.kf.data.mybatis.entity.online.TdxUpIndexOnlineExample" >
    <!--
      WARNING - @mbggenerated
      This element is automatically generated by MyBatis Generator, do not modify.
      This element was generated on Wed Mar 14 15:34:20 CST 2018.
    -->
    delete from tdx_up_index
    <if test="_parameter != null" >
      <include refid="Example_Where_Clause" />
    </if>
  </delete>
  <insert id="insert" parameterType="com.kf.data.mybatis.entity.online.TdxUpIndexOnline" >
    <!--
      WARNING - @mbggenerated
      This element is automatically generated by MyBatis Generator, do not modify.
      This element was generated on Wed Mar 14 15:34:20 CST 2018.
    -->
    <selectKey resultType="java.lang.Integer" keyProperty="id" order="AFTER" >
      SELECT LAST_INSERT_ID()
    </selectKey>
    insert into tdx_up_index (`table`, uptime, upid
      )
    values (#{table,jdbcType=VARCHAR}, #{uptime,jdbcType=TIMESTAMP}, #{upid,jdbcType=INTEGER}
      )
  </insert>
  <insert id="insertSelective" parameterType="com.kf.data.mybatis.entity.online.TdxUpIndexOnline" >
    <!--
      WARNING - @mbggenerated
      This element is automatically generated by MyBatis Generator, do not modify.
      This element was generated on Wed Mar 14 15:34:20 CST 2018.
    -->
    <selectKey resultType="java.lang.Integer" keyProperty="id" order="AFTER" >
      SELECT LAST_INSERT_ID()
    </selectKey>
    insert into tdx_up_index
    <trim prefix="(" suffix=")" suffixOverrides="," >
      <if test="table != null" >
        `table`,
      </if>
      <if test="uptime != null" >
        uptime,
      </if>
      <if test="upid != null" >
        upid,
      </if>
    </trim>
    <trim prefix="values (" suffix=")" suffixOverrides="," >
      <if test="table != null" >
        #{table,jdbcType=VARCHAR},
      </if>
      <if test="uptime != null" >
        #{uptime,jdbcType=TIMESTAMP},
      </if>
      <if test="upid != null" >
        #{upid,jdbcType=INTEGER},
      </if>
    </trim>
  </insert>
  <select id="countByExample" parameterType="com.kf.data.mybatis.entity.online.TdxUpIndexOnlineExample" resultType="java.lang.Integer" >
    <!--
      WARNING - @mbggenerated
      This element is automatically generated by MyBatis Generator, do not modify.
      This element was generated on Wed Mar 14 15:34:20 CST 2018.
    -->
    select count(*) from tdx_up_index
    <if test="_parameter != null" >
      <include refid="Example_Where_Clause" />
    </if>
  </select>
  <update id="updateByExampleSelective" parameterType="map" >
    <!--
      WARNING - @mbggenerated
      This element is automatically generated by MyBatis Generator, do not modify.
      This element was generated on Wed Mar 14 15:34:20 CST 2018.
    -->
    update tdx_up_index
    <set >
      <if test="record.id != null" >
        id = #{record.id,jdbcType=INTEGER},
      </if>
      <if test="record.table != null" >
        `table` = #{record.table,jdbcType=VARCHAR},
      </if>
      <if test="record.uptime != null" >
        uptime = #{record.uptime,jdbcType=TIMESTAMP},
      </if>
      <if test="record.upid != null" >
        upid = #{record.upid,jdbcType=INTEGER},
      </if>
    </set>
    <if test="_parameter != null" >
      <include refid="Update_By_Example_Where_Clause" />
    </if>
  </update>
  <update id="updateByExample" parameterType="map" >
    <!--
      WARNING - @mbggenerated
      This element is automatically generated by MyBatis Generator, do not modify.
      This element was generated on Wed Mar 14 15:34:20 CST 2018.
    -->
    update tdx_up_index
    set id = #{record.id,jdbcType=INTEGER},
      `table` = #{record.table,jdbcType=VARCHAR},
      uptime = #{record.uptime,jdbcType=TIMESTAMP},
      upid = #{record.upid,jdbcType=INTEGER}
    <if test="_parameter != null" >
      <include refid="Update_By_Example_Where_Clause" />
    </if>
  </update>
  <update id="updateByPrimaryKeySelective" parameterType="com.kf.data.mybatis.entity.online.TdxUpIndexOnline" >
    <!--
      WARNING - @mbggenerated
      This element is automatically generated by MyBatis Generator, do not modify.
      This element was generated on Wed Mar 14 15:34:20 CST 2018.
    -->
    update tdx_up_index
    <set >
      <if test="table != null" >
        `table` = #{table,jdbcType=VARCHAR},
      </if>
      <if test="uptime != null" >
        uptime = #{uptime,jdbcType=TIMESTAMP},
      </if>
      <if test="upid != null" >
        upid = #{upid,jdbcType=INTEGER},
      </if>
    </set>
    where id = #{id,jdbcType=INTEGER}
  </update>
  <update id="updateByPrimaryKey" parameterType="com.kf.data.mybatis.entity.online.TdxUpIndexOnline" >
    <!--
      WARNING - @mbggenerated
      This element is automatically generated by MyBatis Generator, do not modify.
      This element was generated on Wed Mar 14 15:34:20 CST 2018.
    -->
    update tdx_up_index
    set `table` = #{table,jdbcType=VARCHAR},
      uptime = #{uptime,jdbcType=TIMESTAMP},
      upid = #{upid,jdbcType=INTEGER}
    where id = #{id,jdbcType=INTEGER}
  </update>
</mapper>